<annotation>
	<folder>naranjas</folder>
	<filename>n112.jpeg</filename>
	<path>/home/matrix-code/Escritorio/EdenSystem/datasets/naranjas/n112.jpeg</path>
	<source>
		<database>Unknown</database>
	</source>
	<size>
		<width>474</width>
		<height>186</height>
		<depth>3</depth>
	</size>
	<segmented>0</segmented>
	<object>
		<name>orange</name>
		<pose>Unspecified</pose>
		<truncated>0</truncated>
		<difficult>0</difficult>
		<bndbox>
			<xmin>58</xmin>
			<ymin>44</ymin>
			<xmax>101</xmax>
			<ymax>85</ymax>
		</bndbox>
	</object>
	<object>
		<name>orange</name>
		<pose>Unspecified</pose>
		<truncated>0</truncated>
		<difficult>0</difficult>
		<bndbox>
			<xmin>19</xmin>
			<ymin>49</ymin>
			<xmax>60</xmax>
			<ymax>97</ymax>
		</bndbox>
	</object>
</annotation>
