<annotation>
	<folder>naranjas</folder>
	<filename>n36.jpeg</filename>
	<path>/home/matrix-code/Escritorio/EdenSystem/datasets/naranjas/n36.jpeg</path>
	<source>
		<database>Unknown</database>
	</source>
	<size>
		<width>474</width>
		<height>434</height>
		<depth>3</depth>
	</size>
	<segmented>0</segmented>
	<object>
		<name>orange</name>
		<pose>Unspecified</pose>
		<truncated>0</truncated>
		<difficult>0</difficult>
		<bndbox>
			<xmin>123</xmin>
			<ymin>104</ymin>
			<xmax>201</xmax>
			<ymax>179</ymax>
		</bndbox>
	</object>
	<object>
		<name>orange</name>
		<pose>Unspecified</pose>
		<truncated>0</truncated>
		<difficult>0</difficult>
		<bndbox>
			<xmin>220</xmin>
			<ymin>132</ymin>
			<xmax>288</xmax>
			<ymax>194</ymax>
		</bndbox>
	</object>
	<object>
		<name>orange</name>
		<pose>Unspecified</pose>
		<truncated>0</truncated>
		<difficult>0</difficult>
		<bndbox>
			<xmin>342</xmin>
			<ymin>94</ymin>
			<xmax>409</xmax>
			<ymax>166</ymax>
		</bndbox>
	</object>
	<object>
		<name>orange</name>
		<pose>Unspecified</pose>
		<truncated>0</truncated>
		<difficult>0</difficult>
		<bndbox>
			<xmin>282</xmin>
			<ymin>125</ymin>
			<xmax>353</xmax>
			<ymax>179</ymax>
		</bndbox>
	</object>
	<object>
		<name>orange</name>
		<pose>Unspecified</pose>
		<truncated>0</truncated>
		<difficult>0</difficult>
		<bndbox>
			<xmin>276</xmin>
			<ymin>169</ymin>
			<xmax>350</xmax>
			<ymax>238</ymax>
		</bndbox>
	</object>
	<object>
		<name>orange</name>
		<pose>Unspecified</pose>
		<truncated>0</truncated>
		<difficult>0</difficult>
		<bndbox>
			<xmin>198</xmin>
			<ymin>76</ymin>
			<xmax>261</xmax>
			<ymax>135</ymax>
		</bndbox>
	</object>
	<object>
		<name>orange</name>
		<pose>Unspecified</pose>
		<truncated>0</truncated>
		<difficult>0</difficult>
		<bndbox>
			<xmin>118</xmin>
			<ymin>77</ymin>
			<xmax>179</xmax>
			<ymax>118</ymax>
		</bndbox>
	</object>
	<object>
		<name>orange</name>
		<pose>Unspecified</pose>
		<truncated>0</truncated>
		<difficult>0</difficult>
		<bndbox>
			<xmin>144</xmin>
			<ymin>165</ymin>
			<xmax>209</xmax>
			<ymax>225</ymax>
		</bndbox>
	</object>
</annotation>
